Metadata-Version: 2.1
Name: Cbloxflip
Version: 0.0.3
Summary: a bloxflip api wrapper that you can use user.send or veiw your info
Home-page: 
Author: itsculty
Author-email: sleepyculty@gmail.com
License: MIT
Keywords: bloxflip,bloxflipApiWrapper,API
Classifier: Development Status :: 5 - Production/Stable
Classifier: Intended Audience :: Education
Classifier: Operating System :: Microsoft :: Windows :: Windows 10
Classifier: License :: OSI Approved :: MIT License
Classifier: Programming Language :: Python :: 3
License-File: LICENCE.txt
